h7_file_finder/__init__.py
h7_file_finder/path_finder.py
h7_file_finder-1.0.1.dist-info/METADATA
h7_file_finder-1.0.1.dist-info/WHEEL
h7_file_finder-1.0.1.dist-info/top_level.txt
h7_file_finder-1.0.1.dist-info/RECORD
