Metadata-Version: 2.4
Name: h7-file-finder
Version: 1.0.1
Summary: Core utility classes for file and path finding in Python projects
Author-email: Roger Mori <roger.mori@example.com>
License: MIT
Project-URL: Homepage, https://github.com/rogermori/h7-file-finder
Project-URL: Bug Tracker, https://github.com/rogermori/h7-file-finder/issues
Classifier: Programming Language :: Python :: 3
Classifier: License :: OSI Approved :: MIT License
Classifier: Operating System :: OS Independent
Requires-Python: >=3.7
